exfunc/__init__.py
exfunc/_hooks/__init__.py
exfunc/_hooks/registration.py
exfunc/_hooks/sdkhooks.py
exfunc/_hooks/types.py
exfunc/_version.py
exfunc/basesdk.py
exfunc/glassdoor.py
exfunc/google.py
exfunc/httpclient.py
exfunc/indeed.py
exfunc/linkedin.py
exfunc/models/__init__.py
exfunc/models/exfuncerror.py
exfunc/models/get_business_reviewsop.py
exfunc/models/get_businessop.py
exfunc/models/get_companyop.py
exfunc/models/get_job_postingop.py
exfunc/models/get_personop.py
exfunc/models/get_product_reviewsop.py
exfunc/models/get_productop.py
exfunc/models/get_propertyop.py
exfunc/models/get_taskop.py
exfunc/models/get_tweetop.py
exfunc/models/get_user_followersop.py
exfunc/models/get_user_tweetsop.py
exfunc/models/get_userop.py
exfunc/models/getuserfollowingsop.py
exfunc/models/glassdoor_search_job_postingsop.py
exfunc/models/glassdoorjobposting.py
exfunc/models/google_get_job_postingop.py
exfunc/models/google_search_job_postingsop.py
exfunc/models/googlejobposting.py
exfunc/models/googlenews.py
exfunc/models/googleproduct.py
exfunc/models/googleproductreview.py
exfunc/models/indeed_search_job_postingsop.py
exfunc/models/indeedjobposting.py
exfunc/models/linkedincompany.py
exfunc/models/linkedincompanyindustry.py
exfunc/models/linkedincompanysize.py
exfunc/models/linkedinjobposting.py
exfunc/models/linkedinperson.py
exfunc/models/navigatortask.py
exfunc/models/no_response_error.py
exfunc/models/responsevalidationerror.py
exfunc/models/scrapeop.py
exfunc/models/sdkerror.py
exfunc/models/search_businessesop.py
exfunc/models/search_companiesop.py
exfunc/models/search_flightsop.py
exfunc/models/search_job_postingsop.py
exfunc/models/search_newsop.py
exfunc/models/search_peopleop.py
exfunc/models/search_productsop.py
exfunc/models/search_propertiesop.py
exfunc/models/search_tweetsop.py
exfunc/models/search_usersop.py
exfunc/models/search_webop.py
exfunc/models/security.py
exfunc/models/servererror.py
exfunc/models/skyscannerairport.py
exfunc/models/skyscannercarrier.py
exfunc-0.8.0.dist-info/METADATA
exfunc-0.8.0.dist-info/WHEEL
exfunc-0.8.0.dist-info/RECORD
